michaelPanExpediteLib/__init__.py
michaelPanExpediteLib/expedite_array_circulation.py
michaelPanExpediteLib-0.0.3.dist-info/LICENSE
michaelPanExpediteLib-0.0.3.dist-info/METADATA
michaelPanExpediteLib-0.0.3.dist-info/WHEEL
michaelPanExpediteLib-0.0.3.dist-info/top_level.txt
michaelPanExpediteLib-0.0.3.dist-info/RECORD
